jsonrpcdb/__init__.py
jsonrpcdb/auth.py
jsonrpcdb/connection.py
jsonrpcdb/cursor.py
jsonrpcdb/error.py
jsonrpcdb/tests/__init__.py
jsonrpcdb/tests/server.py
jsonrpcdb/tests/test_auth.py
jsonrpcdb/tests/test_connection.py
jsonrpcdb/tests/test_cursor.py
jsonrpcdb-0.1.5.dist-info/DESCRIPTION.rst
jsonrpcdb-0.1.5.dist-info/METADATA
jsonrpcdb-0.1.5.dist-info/RECORD
jsonrpcdb-0.1.5.dist-info/WHEEL
jsonrpcdb-0.1.5.dist-info/metadata.json
jsonrpcdb-0.1.5.dist-info/top_level.txt
