Metadata-Version: 2.0
Name: jsonrpcdb
Version: 0.1.5
Summary: DB API v2.0 for JSON-RPC
Home-page: https://github.com/LiveStalker/json-rpc-db
Author: Alexey V. Grebenshchikov
Author-email: mi.aleksio@gmail.com
License: MIT
Keywords: db-api json-rpc
Platform: UNKNOWN
Classifier: Development Status :: 4 - Beta
Classifier: Environment :: Console
Classifier: Operating System :: OS Independent
Classifier: Intended Audience :: Developers
Classifier: Topic :: Database
Classifier: Topic :: Database :: Front-Ends
Classifier: Topic :: Software Development
Classifier: Topic :: Software Development :: Libraries :: Python Modules
Classifier: License :: OSI Approved :: MIT License
Requires-Dist: requests
Provides-Extra: test
Requires-Dist: coverage; extra == 'test'
Requires-Dist: json-rpc; extra == 'test'
Requires-Dist: werkzeug; extra == 'test'
